[
    {"artist": "Adele", "title": "Rolling in the Deep"},
    {"artist": "Beyoncé", "title": "Crazy in Love"},
    {"artist": "Bruno Mars", "title": "Uptown Funk"},
    {"artist": "Coldplay", "title": "Fix You"},
    {"artist": "Dua Lipa", "title": "Don't Start Now"},
    {"artist": "Ed Sheeran", "title": "Shape of You"},
    {"artist": "Elton John", "title": "Rocket Man"},
    {"artist": "Eminem", "title": "Lose Yourself"},
    {"artist": "Lady Gaga", "title": "Bad Romance"},
    {"artist": "Lil Nas X", "title": "Old Town Road"},
    {"artist": "Maroon 5", "title": "Sugar"},
    {"artist": "Michael Jackson", "title": "Billie Jean"},
    {"artist": "Miley Cyrus", "title": "Wrecking Ball"},
    {"artist": "Post Malone", "title": "Circles"},
    {"artist": "Rihanna", "title": "Umbrella"},
    {"artist": "Sam Smith", "title": "Stay With Me"},
    {"artist": "Sia", "title": "Chandelier"},
    {"artist": "Taylor Swift", "title": "Shake It Off"},
    {"artist": "The Weeknd", "title": "Blinding Lights"},
    {"artist": "Travis Scott", "title": "SICKO MODE"},
    {"artist": "Whitney Houston", "title": "I Will Always Love You"},
    {"artist": "Katy Perry", "title": "Firework"},
    {"artist": "Justin Bieber", "title": "Sorry"},
    {"artist": "Imagine Dragons", "title": "Believer"},
    {"artist": "Linkin Park", "title": "Numb"},
    {"artist": "Drake", "title": "God's Plan"},
    {"artist": "Maroon 5", "title": "Girls Like You"},
    {"artist": "Nicki Minaj", "title": "Super Bass"},
    {"artist": "Billie Eilish", "title": "Bad Guy"},
    {"artist": "OneRepublic", "title": "Counting Stars"},
    {"artist": "Halsey", "title": "Without Me"},
    {"artist": "Shawn Mendes", "title": "Stitches"},
    {"artist": "Kendrick Lamar", "title": "HUMBLE."},
    {"artist": "Demi Lovato", "title": "Sorry Not Sorry"},
    {"artist": "Post Malone", "title": "Rockstar"},
    {"artist": "Travis Scott", "title": "Goosebumps"},
    {"artist": "Ariana Grande", "title": "Thank U, Next"},
    {"artist": "Billie Eilish", "title": "When the Party's Over"},
    {"artist": "Zayn", "title": "Dusk Till Dawn"},
    {"artist": "Imagine Dragons", "title": "Thunder"},
    {"artist": "Fifth Harmony", "title": "Work from Home"},
    {"artist": "Bebe Rexha", "title": "Meant to Be"},
    {"artist": "Charlie Puth", "title": "Attention"},
    {"artist": "Khalid", "title": "Young Dumb & Broke"},
    {"artist": "Selena Gomez", "title": "Lose You to Love Me"},
    {"artist": "Ariana Grande", "title": "7 rings"},
    {"artist": "Snoop Dogg", "title": "Drop It Like It's Hot"},
    {"artist": "T-Pain", "title": "Buy U a Drank"},
    {"artist": "Nelly", "title": "Hot in Herre"},
    {"artist": "Katy Perry", "title": "Last Friday Night"},
    {"artist": "Shakira", "title": "Hips Don't Lie"},
    {"artist": "Lizzo", "title": "Truth Hurts"},
    {"artist": "Justin Timberlake", "title": "Can't Stop the Feeling!"},
    {"artist": "Alicia Keys", "title": "Fallin'"},
    {"artist": "Usher", "title": "Yeah!"},
    {"artist": "Marshmello", "title": "Happier"}
]
